Metadata-Version: 2.1
Name: qshader
Version: 1.0.0
Summary: QShader - Shaders support for 2D PyQt Games.
Home-page: https://github.com/xzripper/qshader
Download-URL: https://github.com/xzripper/qshader/archive/refs/tags/v1.0.0-alpha.tar.gz
Author: Ivan Perzhinsky.
Author-email: name1not1found.com@gmail.com
License: MIT
Keywords: pyqt,qt,shaders,games,2d
Classifier: Development Status :: 3 - Alpha
Classifier: Intended Audience :: Developers
Classifier: Topic :: Games/Entertainment
Classifier: License :: OSI Approved :: MIT License
Classifier: Programming Language :: Python :: 3
License-File: LICENSE.txt
